swh/scheduler/__init__.py
swh/scheduler/backend.py
swh/scheduler/cli_utils.py
swh/scheduler/conftest.py
swh/scheduler/exc.py
swh/scheduler/in_memory.py
swh/scheduler/interface.py
swh/scheduler/journal_client.py
swh/scheduler/model.py
swh/scheduler/py.typed
swh/scheduler/pytest_plugin.py
swh/scheduler/task.py
swh/scheduler/utils.py
swh/scheduler/api/__init__.py
swh/scheduler/api/client.py
swh/scheduler/api/serializers.py
swh/scheduler/api/server.py
swh/scheduler/celery_backend/__init__.py
swh/scheduler/celery_backend/config.py
swh/scheduler/celery_backend/first_visits.py
swh/scheduler/celery_backend/pika_listener.py
swh/scheduler/celery_backend/recurrent_visits.py
swh/scheduler/celery_backend/runner.py
swh/scheduler/celery_backend/utils.py
swh/scheduler/cli/__init__.py
swh/scheduler/cli/add_forge_now.py
swh/scheduler/cli/admin.py
swh/scheduler/cli/celery_monitor.py
swh/scheduler/cli/config.py
swh/scheduler/cli/journal.py
swh/scheduler/cli/origin.py
swh/scheduler/cli/origin_utils.py
swh/scheduler/cli/simulator.py
swh/scheduler/cli/task.py
swh/scheduler/cli/task_type.py
swh/scheduler/cli/utils.py
swh/scheduler/simulator/__init__.py
swh/scheduler/simulator/common.py
swh/scheduler/simulator/origin_scheduler.py
swh/scheduler/simulator/origins.py
swh/scheduler/simulator/task_scheduler.py
swh/scheduler/sql/10-superuser-init.sql
swh/scheduler/sql/30-schema.sql
swh/scheduler/sql/40-func.sql
swh/scheduler/sql/60-indexes.sql
swh/scheduler/sql/__init__.py
swh/scheduler/sql/upgrades/02.sql
swh/scheduler/sql/upgrades/03.sql
swh/scheduler/sql/upgrades/04.sql
swh/scheduler/sql/upgrades/05.sql
swh/scheduler/sql/upgrades/06.sql
swh/scheduler/sql/upgrades/07.sql
swh/scheduler/sql/upgrades/08.sql
swh/scheduler/sql/upgrades/09.sql
swh/scheduler/sql/upgrades/10.sql
swh/scheduler/sql/upgrades/11.sql
swh/scheduler/sql/upgrades/12.sql
swh/scheduler/sql/upgrades/13.sql
swh/scheduler/sql/upgrades/14.sql
swh/scheduler/sql/upgrades/15.sql
swh/scheduler/sql/upgrades/16.sql
swh_scheduler-3.3.0.dist-info/licenses/AUTHORS
swh_scheduler-3.3.0.dist-info/licenses/LICENSE
swh_scheduler-3.3.0.dist-info/licenses/LICENSE.Celery
swh_scheduler-3.3.0.dist-info/METADATA
swh_scheduler-3.3.0.dist-info/WHEEL
swh_scheduler-3.3.0.dist-info/entry_points.txt
swh_scheduler-3.3.0.dist-info/top_level.txt
swh_scheduler-3.3.0.dist-info/RECORD
